cal.py
cal_plusplus-1.0.0.dist-info/METADATA
cal_plusplus-1.0.0.dist-info/WHEEL
cal_plusplus-1.0.0.dist-info/entry_points.txt
cal_plusplus-1.0.0.dist-info/top_level.txt
cal_plusplus-1.0.0.dist-info/RECORD
