Metadata-Version: 2.1
Name: cal-plusplus
Version: 1.0.0
Summary: A cal replacement that includes working days
Home-page: https://github.com/sesh/cal-plusplus
Author: Brenton Cleeland
Author-email: brenton@brntn.me
Project-URL: Bug Tracker, https://github.com/sesh/cal-plusplus/issues
Classifier: Programming Language :: Python :: 3
Requires-Python: >=3.7
Requires-Dist: workalendar
